audio2vec/__init__.py
audio2vec/audio2vec.py
audio2vec-0.6.16.dist-info/METADATA
audio2vec-0.6.16.dist-info/WHEEL
audio2vec-0.6.16.dist-info/top_level.txt
audio2vec-0.6.16.dist-info/RECORD
