Metadata-Version: 2.1
Name: audio2vec
Version: 0.6.16
Summary: An Audio2Vec annotation library
Home-page: https://github.com/dallo7/audio2Vec.git
Author: Dalmas Chituyi
Author-email: cwakhusama@gmail.com
License: GPL version 3, excluding DRM provisions
Requires-Dist: setuptools
Requires-Dist: pandas
Requires-Dist: scikit-learn
